{
    "pools": [
        {
            "rolls": 1,
            "entries": [
                {
                    "type": "minecraft:item",
                    "name": "written_book",
                    "functions": [
                        {
                            "function": "minecraft:set_written_book_pages",
                            "pages": [
                                [
                                    "",
                                    {
                                        "text": "♦ Sorrow Soul",
                                        "color": "black",
                                        "bold": true
                                    },
                                    "\n",
                                    {
                                        "text": "                        ",
                                        "color": "black",
                                        "strikethrough": true
                                    },
                                    "\n",
                                    {
                                        "text": "█ ",
                                        "color": "gray",
                                        "extra": [
                                            {
                                                "translate": "item.minecraft.ghast_tear",
                                                "color": "black",
                                                "extra": [
                                                    {
                                                        "text": " ×1",
                                                        "color": "black"
                                                    }
                                                ]
                                            }
                                        ]
                                    },
                                    "\n",
                                    "\n",
                                    "\n",
                                    "\n",
                                    "\n",
                                    "\n",
                                    {
                                        "text": "                        ",
                                        "color": "black",
                                        "strikethrough": true
                                    },
                                    "\n",
                                    {
                                        "text": "♦ Pattern",
                                        "color": "black",
                                        "bold": true
                                    },
                                    "\n",
                                    {
                                        "text": "　　　　█",
                                        "color": "white",
                                        "extra": [
                                            {
                                                "text": "█",
                                                "color": "gray",
                                                "extra": [
                                                    {
                                                        "text": "█",
                                                        "color": "white"
                                                    }
                                                ]
                                            }
                                        ]
                                    },
                                    "\n",
                                    {
                                        "text": "　　　　█",
                                        "color": "gray",
                                        "extra": [
                                            {
                                                "text": "█",
                                                "color": "gray",
                                                "extra": [
                                                    {
                                                        "text": "█",
                                                        "color": "gray"
                                                    }
                                                ]
                                            }
                                        ]
                                    },
                                    "\n",
                                    {
                                        "text": "　　　　█",
                                        "color": "white",
                                        "extra": [
                                            {
                                                "text": "█",
                                                "color": "gray",
                                                "extra": [
                                                    {
                                                        "text": "█",
                                                        "color": "white"
                                                    }
                                                ]
                                            }
                                        ]
                                    }
                                ],
                                [
                                    "",
                                    {
                                        "text": "♦ Sorrow Helmet",
                                        "color": "black",
                                        "bold": true
                                    },
                                    "\n",
                                    {
                                        "text": "                        ",
                                        "color": "black",
                                        "strikethrough": true
                                    },
                                    "\n",
                                    {
                                        "text": "█ ",
                                        "color": "gray",
                                        "extra": [
                                            {
                                                "text": "Cobblestone Helmet",
                                                "color": "black",
                                                "extra": [
                                                    {
                                                        "text": " ×1",
                                                        "color": "black"
                                                    }
                                                ]
                                            }
                                        ]
                                    },
                                    "\n",
                                    {
                                        "text": "█ ",
                                        "color": "dark_purple",
                                        "extra": [
                                            {
                                                "text": "Sorrow Soul",
                                                "color": "black",
                                                "extra": [
                                                    {
                                                        "text": " ×1",
                                                        "color": "black"
                                                    }
                                                ]
                                            }
                                        ]
                                    },
                                    "\n",
                                    "\n",
                                    "\n",
                                    "\n",
                                    {
                                        "text": "                        ",
                                        "color": "black",
                                        "strikethrough": true
                                    },
                                    "\n",
                                    {
                                        "text": "♦ Pattern",
                                        "color": "black",
                                        "bold": true
                                    },
                                    "\n",
                                    {
                                        "text": "　　　　█",
                                        "color": "white",
                                        "extra": [
                                            {
                                                "text": "█",
                                                "color": "dark_purple",
                                                "extra": [
                                                    {
                                                        "text": "█",
                                                        "color": "white"
                                                    }
                                                ]
                                            }
                                        ]
                                    },
                                    "\n",
                                    {
                                        "text": "　　　　█",
                                        "color": "dark_purple",
                                        "extra": [
                                            {
                                                "text": "█",
                                                "color": "gray",
                                                "extra": [
                                                    {
                                                        "text": "█",
                                                        "color": "dark_purple"
                                                    }
                                                ]
                                            }
                                        ]
                                    },
                                    "\n",
                                    {
                                        "text": "　　　　█",
                                        "color": "white",
                                        "extra": [
                                            {
                                                "text": "█",
                                                "color": "dark_purple",
                                                "extra": [
                                                    {
                                                        "text": "█",
                                                        "color": "white"
                                                    }
                                                ]
                                            }
                                        ]
                                    }
                                ],
                                [
                                    "",
                                    {
                                        "text": "♦ Sorrow Chestplate",
                                        "color": "black",
                                        "bold": true
                                    },
                                    "\n",
                                    {
                                        "text": "                        ",
                                        "color": "black",
                                        "strikethrough": true
                                    },
                                    "\n",
                                    {
                                        "text": "█ ",
                                        "color": "gray",
                                        "extra": [
                                            {
                                                "text": "Cobblestone Chestplate",
                                                "color": "black",
                                                "extra": [
                                                    {
                                                        "text": " ×1",
                                                        "color": "black"
                                                    }
                                                ]
                                            }
                                        ]
                                    },
                                    "\n",
                                    {
                                        "text": "█ ",
                                        "color": "dark_purple",
                                        "extra": [
                                            {
                                                "text": "Sorrow Soul",
                                                "color": "black",
                                                "extra": [
                                                    {
                                                        "text": " ×1",
                                                        "color": "black"
                                                    }
                                                ]
                                            }
                                        ]
                                    },
                                    "\n",
                                    "\n",
                                    "\n",
                                    {
                                        "text": "                        ",
                                        "color": "black",
                                        "strikethrough": true
                                    },
                                    "\n",
                                    {
                                        "text": "♦ Pattern",
                                        "color": "black",
                                        "bold": true
                                    },
                                    "\n",
                                    {
                                        "text": "　　　　█",
                                        "color": "white",
                                        "extra": [
                                            {
                                                "text": "█",
                                                "color": "dark_purple",
                                                "extra": [
                                                    {
                                                        "text": "█",
                                                        "color": "white"
                                                    }
                                                ]
                                            }
                                        ]
                                    },
                                    "\n",
                                    {
                                        "text": "　　　　█",
                                        "color": "dark_purple",
                                        "extra": [
                                            {
                                                "text": "█",
                                                "color": "gray",
                                                "extra": [
                                                    {
                                                        "text": "█",
                                                        "color": "dark_purple"
                                                    }
                                                ]
                                            }
                                        ]
                                    },
                                    "\n",
                                    {
                                        "text": "　　　　█",
                                        "color": "white",
                                        "extra": [
                                            {
                                                "text": "█",
                                                "color": "dark_purple",
                                                "extra": [
                                                    {
                                                        "text": "█",
                                                        "color": "white"
                                                    }
                                                ]
                                            }
                                        ]
                                    }
                                ],
                                [
                                    "",
                                    {
                                        "text": "♦ Sorrow Leggings",
                                        "color": "black",
                                        "bold": true
                                    },
                                    "\n",
                                    {
                                        "text": "                        ",
                                        "color": "black",
                                        "strikethrough": true
                                    },
                                    "\n",
                                    {
                                        "text": "█ ",
                                        "color": "gray",
                                        "extra": [
                                            {
                                                "text": "Cobblestone Leggings",
                                                "color": "black",
                                                "extra": [
                                                    {
                                                        "text": " ×1",
                                                        "color": "black"
                                                    }
                                                ]
                                            }
                                        ]
                                    },
                                    "\n",
                                    {
                                        "text": "█ ",
                                        "color": "dark_purple",
                                        "extra": [
                                            {
                                                "text": "Sorrow Soul",
                                                "color": "black",
                                                "extra": [
                                                    {
                                                        "text": " ×1",
                                                        "color": "black"
                                                    }
                                                ]
                                            }
                                        ]
                                    },
                                    "\n",
                                    "\n",
                                    "\n",
                                    "\n",
                                    {
                                        "text": "                        ",
                                        "color": "black",
                                        "strikethrough": true
                                    },
                                    "\n",
                                    {
                                        "text": "♦ Pattern",
                                        "color": "black",
                                        "bold": true
                                    },
                                    "\n",
                                    {
                                        "text": "　　　　█",
                                        "color": "white",
                                        "extra": [
                                            {
                                                "text": "█",
                                                "color": "dark_purple",
                                                "extra": [
                                                    {
                                                        "text": "█",
                                                        "color": "white"
                                                    }
                                                ]
                                            }
                                        ]
                                    },
                                    "\n",
                                    {
                                        "text": "　　　　█",
                                        "color": "dark_purple",
                                        "extra": [
                                            {
                                                "text": "█",
                                                "color": "gray",
                                                "extra": [
                                                    {
                                                        "text": "█",
                                                        "color": "dark_purple"
                                                    }
                                                ]
                                            }
                                        ]
                                    },
                                    "\n",
                                    {
                                        "text": "　　　　█",
                                        "color": "white",
                                        "extra": [
                                            {
                                                "text": "█",
                                                "color": "dark_purple",
                                                "extra": [
                                                    {
                                                        "text": "█",
                                                        "color": "white"
                                                    }
                                                ]
                                            }
                                        ]
                                    }
                                ],
                                [
                                    "",
                                    {
                                        "text": "♦ Sorrow Boots",
                                        "color": "black",
                                        "bold": true
                                    },
                                    "\n",
                                    {
                                        "text": "                        ",
                                        "color": "black",
                                        "strikethrough": true
                                    },
                                    "\n",
                                    {
                                        "text": "█ ",
                                        "color": "gray",
                                        "extra": [
                                            {
                                                "text": "Cobblestone Boots",
                                                "color": "black",
                                                "extra": [
                                                    {
                                                        "text": " ×1",
                                                        "color": "black"
                                                    }
                                                ]
                                            }
                                        ]
                                    },
                                    "\n",
                                    {
                                        "text": "█ ",
                                        "color": "dark_purple",
                                        "extra": [
                                            {
                                                "text": "Sorrow Soul",
                                                "color": "black",
                                                "extra": [
                                                    {
                                                        "text": " ×1",
                                                        "color": "black"
                                                    }
                                                ]
                                            }
                                        ]
                                    },
                                    "\n",
                                    "\n",
                                    "\n",
                                    "\n",
                                    {
                                        "text": "                        ",
                                        "color": "black",
                                        "strikethrough": true
                                    },
                                    "\n",
                                    {
                                        "text": "♦ Pattern",
                                        "color": "black",
                                        "bold": true
                                    },
                                    "\n",
                                    {
                                        "text": "　　　　█",
                                        "color": "white",
                                        "extra": [
                                            {
                                                "text": "█",
                                                "color": "dark_purple",
                                                "extra": [
                                                    {
                                                        "text": "█",
                                                        "color": "white"
                                                    }
                                                ]
                                            }
                                        ]
                                    },
                                    "\n",
                                    {
                                        "text": "　　　　█",
                                        "color": "dark_purple",
                                        "extra": [
                                            {
                                                "text": "█",
                                                "color": "gray",
                                                "extra": [
                                                    {
                                                        "text": "█",
                                                        "color": "dark_purple"
                                                    }
                                                ]
                                            }
                                        ]
                                    },
                                    "\n",
                                    {
                                        "text": "　　　　█",
                                        "color": "white",
                                        "extra": [
                                            {
                                                "text": "█",
                                                "color": "dark_purple",
                                                "extra": [
                                                    {
                                                        "text": "█",
                                                        "color": "white"
                                                    }
                                                ]
                                            }
                                        ]
                                    }
                                ],
                                [
                                    "",
                                    {
                                        "text": "♦ Sorrow Sword",
                                        "color": "black",
                                        "bold": true
                                    },
                                    "\n",
                                    {
                                        "text": "                        ",
                                        "color": "black",
                                        "strikethrough": true
                                    },
                                    "\n",
                                    {
                                        "text": "█ ",
                                        "color": "dark_purple",
                                        "extra": [
                                            {
                                                "text": "Sorrow Soul",
                                                "color": "black",
                                                "extra": [
                                                    {
                                                        "text": " ×1",
                                                        "color": "black"
                                                    }
                                                ]
                                            }
                                        ]
                                    },
                                    "\n",
                                    {
                                        "text": "█ ",
                                        "color": "gold",
                                        "extra": [
                                            {
                                                "translate": "item.minecraft.blaze_rod",
                                                "color": "black",
                                                "extra": [
                                                    {
                                                        "text": " ×1",
                                                        "color": "black"
                                                    }
                                                ]
                                            }
                                        ]
                                    },
                                    "\n",
                                    "\n",
                                    "\n",
                                    "\n",
                                    "\n",
                                    {
                                        "text": "                        ",
                                        "color": "black",
                                        "strikethrough": true
                                    },
                                    "\n",
                                    {
                                        "text": "♦ Pattern",
                                        "color": "black",
                                        "bold": true
                                    },
                                    "\n",
                                    {
                                        "text": "　　　　█",
                                        "color": "white",
                                        "extra": [
                                            {
                                                "text": "█",
                                                "color": "dark_purple",
                                                "extra": [
                                                    {
                                                        "text": "█",
                                                        "color": "white"
                                                    }
                                                ]
                                            }
                                        ]
                                    },
                                    "\n",
                                    {
                                        "text": "　　　　█",
                                        "color": "white",
                                        "extra": [
                                            {
                                                "text": "█",
                                                "color": "dark_purple",
                                                "extra": [
                                                    {
                                                        "text": "█",
                                                        "color": "white"
                                                    }
                                                ]
                                            }
                                        ]
                                    },
                                    "\n",
                                    {
                                        "text": "　　　　█",
                                        "color": "white",
                                        "extra": [
                                            {
                                                "text": "█",
                                                "color": "gold",
                                                "extra": [
                                                    {
                                                        "text": "█",
                                                        "color": "white"
                                                    }
                                                ]
                                            }
                                        ]
                                    }
                                ],
                                [
                                    "",
                                    {
                                        "text": "♦ Sorrow Bow",
                                        "color": "black",
                                        "bold": true
                                    },
                                    "\n",
                                    {
                                        "text": "                        ",
                                        "color": "black",
                                        "strikethrough": true
                                    },
                                    "\n",
                                    {
                                        "text": "█ ",
                                        "color": "dark_purple",
                                        "extra": [
                                            {
                                                "text": "Sorrow Soul",
                                                "color": "black",
                                                "extra": [
                                                    {
                                                        "text": " ×1",
                                                        "color": "black"
                                                    }
                                                ]
                                            }
                                        ]
                                    },
                                    "\n",
                                    {
                                        "text": "█ ",
                                        "color": "gold",
                                        "extra": [
                                            {
                                                "text": "Crimson Alloy",
                                                "color": "black",
                                                "extra": [
                                                    {
                                                        "text": " ×1",
                                                        "color": "black"
                                                    }
                                                ]
                                            }
                                        ]
                                    },
                                    "\n",
                                    "\n",
                                    "\n",
                                    "\n",
                                    "\n",
                                    {
                                        "text": "                        ",
                                        "color": "black",
                                        "strikethrough": true
                                    },
                                    "\n",
                                    {
                                        "text": "♦ Pattern",
                                        "color": "black",
                                        "bold": true
                                    },
                                    "\n",
                                    {
                                        "text": "　　　　█",
                                        "color": "white",
                                        "extra": [
                                            {
                                                "text": "█",
                                                "color": "gold",
                                                "extra": [
                                                    {
                                                        "text": "█",
                                                        "color": "dark_purple"
                                                    }
                                                ]
                                            }
                                        ]
                                    },
                                    "\n",
                                    {
                                        "text": "　　　　█",
                                        "color": "gold",
                                        "extra": [
                                            {
                                                "text": "█",
                                                "color": "white",
                                                "extra": [
                                                    {
                                                        "text": "█",
                                                        "color": "dark_purple"
                                                    }
                                                ]
                                            }
                                        ]
                                    },
                                    "\n",
                                    {
                                        "text": "　　　　█",
                                        "color": "white",
                                        "extra": [
                                            {
                                                "text": "█",
                                                "color": "gold",
                                                "extra": [
                                                    {
                                                        "text": "█",
                                                        "color": "dark_purple"
                                                    }
                                                ]
                                            }
                                        ]
                                    }
                                ],
                                [
                                    "",
                                    {
                                        "text": "♦ §kDragon Series§r",
                                        "color": "black",
                                        "bold": true
                                    },
                                    "\n",
                                    {
                                        "text": "                        ",
                                        "color": "black",
                                        "strikethrough": true
                                    },
                                    "\n",
                                    {
                                        "text": "█ ",
                                        "color": "black",
                                        "extra": [
                                            {
                                                "text": "Dragon Fragment",
                                                "color": "black",
                                                "extra": [
                                                    {
                                                        "text": " ×1",
                                                        "color": "black"
                                                    }
                                                ]
                                            }
                                        ]
                                    },
                                    "\n",
                                    {
                                        "text": "█ ",
                                        "color": "#663300",
                                        "extra": [
                                            {
                                                "translate": "item.minecraft.writable_book",
                                                "color": "black",
                                                "extra": [
                                                    {
                                                        "text": " ×1",
                                                        "color": "black"
                                                    }
                                                ]
                                            }
                                        ]
                                    },
                                    "\n",
                                    "\n",
                                    "\n",
                                    "\n",
                                    {
                                        "text": "                        ",
                                        "color": "black",
                                        "strikethrough": true
                                    },
                                    "\n",
                                    {
                                        "text": "♦ Pattern",
                                        "color": "black",
                                        "bold": true
                                    },
                                    "\n",
                                    {
                                        "text": "　　　　█",
                                        "color": "black",
                                        "extra": [
                                            {
                                                "text": "█",
                                                "color": "black",
                                                "extra": [
                                                    {
                                                        "text": "█",
                                                        "color": "black"
                                                    }
                                                ]
                                            }
                                        ]
                                    },
                                    "\n",
                                    {
                                        "text": "　　　　█",
                                        "color": "black",
                                        "extra": [
                                            {
                                                "text": "█",
                                                "color": "#663300",
                                                "extra": [
                                                    {
                                                        "text": "█",
                                                        "color": "black"
                                                    }
                                                ]
                                            }
                                        ]
                                    },
                                    "\n",
                                    {
                                        "text": "　　　　█",
                                        "color": "black",
                                        "extra": [
                                            {
                                                "text": "█",
                                                "color": "black",
                                                "extra": [
                                                    {
                                                        "text": "█",
                                                        "color": "black"
                                                    }
                                                ]
                                            }
                                        ]
                                    }
                                ]
                            ],
                            "mode": "replace_all"
                        },
                        {
                            "function": "minecraft:set_lore",
                            "entity": "this",
                            "lore": [
                                {
                                    "text": "Recipes of Sorrow Series",
                                    "color": "gray",
                                    "italic": false
                                },
                                {
                                    "text": "are written.",
                                    "color": "gray",
                                    "italic": false
                                },
                                {
                                    "text": "                         ",
                                    "color": "dark_gray",
                                    "strikethrough": true
                                },
                                {
                                    "text": "‣ Recipe book",
                                    "extra": [
                                        {
                                            "text": "【",
                                            "extra": [
                                                {
                                                    "text": "✪✪✪✪✪",
                                                    "color": "gold",
                                                    "extra": [
                                                        {
                                                            "text": "】",
                                                            "color": "white"
                                                        }
                                                    ]
                                                }
                                            ]
                                        }
                                    ],
                                    "color": "white",
                                    "italic": false
                                }
                            ],
                            "mode": "replace_all"
                        },
                        {
                            "function": "minecraft:set_custom_data",
                            "tag": "{donpig_ab:{asset:{item:{custom_item:1b,custom_item_id:\"sorrow_series_recipe_book\"}}}}"
                        },
                        {
                            "function": "minecraft:set_name",
                            "entity": "this",
                            "target": "item_name",
                            "name": {
                                "text": "Sorrow Series",
                                "color": "gold",
                                "italic": false
                            }
                        }
                    ]
                }
            ]
        }
    ]
}
